.gitignore
COPYING
MANIFEST.in
NEWS.txt
README.txt
gtimelog
gtimelog.desktop
gtimelog.spec
runtests
setup.cfg
setup.py
src/cooltimelog.egg-info/PKG-INFO
src/cooltimelog.egg-info/SOURCES.txt
src/cooltimelog.egg-info/dependency_links.txt
src/cooltimelog.egg-info/entry_points.txt
src/cooltimelog.egg-info/not-zip-safe
src/cooltimelog.egg-info/requires.txt
src/cooltimelog.egg-info/top_level.txt
src/gtimelog/__init__.py
src/gtimelog/collabora.py
src/gtimelog/gtimelog.png
src/gtimelog/gtimelog.ui
src/gtimelog/main.py
src/gtimelog/paths.py
src/gtimelog/rltimelog.py
src/gtimelog/secrets.py
src/gtimelog/settings.py
src/gtimelog/timelog.py
src/gtimelog/tzoffset.py
src/gtimelog/utils.py
src/gtimelog/tests/__init__.py
src/gtimelog/tests/__main__.py
src/gtimelog/tests/test_timelog.py