Metadata-Version: 2.4
Name: cooltimelog
Version: 0.0.0
Summary: fork of collabora's gtimelog with a cleaner tasks pane and support for changing default paths through environment variables
Home-page: https://gtimelog.org/
Author: Sahil Gautam
Author-email: sahil.gautam@collabora.com
License: GPL
Keywords: time log logging timesheets gnome gtk
Classifier: Development Status :: 4 - Beta
Classifier: Environment :: X11 Applications :: GTK
Classifier: License :: OSI Approved :: GNU General Public License (GPL)
Classifier: Programming Language :: Python :: 3.6
Classifier: Programming Language :: Python :: 3.7
Classifier: Programming Language :: Python :: 3.8
Classifier: Programming Language :: Python :: Implementation :: CPython
Classifier: Programming Language :: Python :: Implementation :: PyPy
Classifier: Topic :: Office/Business
Requires-Python: >= 3.6
License-File: COPYING
Requires-Dist: PyGObject
Dynamic: author
Dynamic: author-email
Dynamic: classifier
Dynamic: description
Dynamic: home-page
Dynamic: keywords
Dynamic: license
Dynamic: license-file
Dynamic: requires-dist
Dynamic: requires-python
Dynamic: summary
